{
    "vb": "1.0.0",
    "timestamp": 1652635725821,
    "settings": {
        "authProvider": "jwt",
        "logo": "ZedSMS",
        "version": "fluent",
        "theme": "default",
        "locale": "en-US",
        "isSidebarOpen": false,
        "isSupportChatOpen": false,
        "isMobileView": false,
        "isMobileMenuOpen": false,
        "isMenuCollapsed": true,
        "isPreselectedOpen": false,
        "preselectedVariant": "default",
        "menuLayoutType": "left",
        "routerAnimation": "slide-fadein-up",
        "menuColor": "gray",
        "authPagesColor": "gray",
        "isAuthTopbar": true,
        "primaryColor": "#4b7cf3",
        "leftMenuWidth": 256,
        "isMenuUnfixed": false,
        "isMenuShadow": false,
        "isTopbarFixed": false,
        "isTopbarSeparated": false,
        "isGrayTopbar": false,
        "isContentMaxWidth": false,
        "isAppMaxWidth": false,
        "isGrayBackground": false,
        "isCardShadow": true,
        "isSquaredBorders": false,
        "isBorderless": false,
        "layoutMenu": "classic",
        "layoutTopbar": "v1",
        "layoutBreadcrumbs": "v1",
        "layoutFooter": "v1",
        "flyoutMenuType": "flyout",
        "flyoutMenuColor": "blue"
    },
    "config": [{
            "key": "__dashboard",
            "title": "Dashboard",
            "url": "/dashboard",
            "icon": "fe fe-home"
        },
        {
            "title": "Sms",
            "url": "/sms",
            "icon": "fe fe-mail",
            "key": "t6vu64"
        },
        {
            "title": "Contacts",
            "url": "/contacts",
            "icon": "fe fe-users",
            "key": "igsw7m"
        },
        {
            "title": "Account",
            "url": "/account",
            "icon": "fe fe-archive",
            "key": "dfflre"
        },
        {
            "title": "Subscription",
            "url": "/subscription",
            "icon": "fe fe-dollar-sign",
            "key": "t44kvu"
        }
    ],
    "content": {
        "t6vu64": [{
                "key": "m6cph",
                "columns": [{
                    "key": "18hqct",
                    "className": "col-lg-12",
                    "cards": [{
                        "key": "0kmxt",
                        "extraClass": "card card-top card-top-success",
                        "widgets": [{
                            "key": "f1ofz",
                            "name": "Headers-CardHeader",
                            "editable": true,
                            "dataType": "object",
                            "wrapper": "card-header",
                            "data": {
                                "title": "Welocome to the SMS section"
                            }
                        }]
                    }]
                }]
            },
            {
                "key": "8aj6om",
                "columns": [{
                        "key": "anaj4b",
                        "className": "col-lg-4 col-md-12",
                        "cards": [{
                            "key": "9vqgl",
                            "extraClass": "card card-top card-top-primary",
                            "widgets": [{
                                    "key": "h4sw0r",
                                    "name": "Headers-Heading",
                                    "editable": true,
                                    "dataType": "object",
                                    "wrapper": "card-header",
                                    "data": {
                                        "title": "Delivered SMS"
                                    }
                                },
                                {
                                    "key": "lg4omog",
                                    "name": "WidgetsTables-5"
                                }
                            ]
                        }]
                    },
                    {
                        "key": "n3omfk",
                        "className": "col-lg-4 col-md-12",
                        "cards": [{
                            "key": "qfej75",
                            "extraClass": "card card-top card-top-primary",
                            "widgets": [{
                                    "key": "t1rffs",
                                    "name": "Headers-Heading",
                                    "editable": true,
                                    "dataType": "object",
                                    "wrapper": "card-header",
                                    "data": {
                                        "title": "Send New SMS"
                                    }
                                },
                                {
                                    "key": "nptpw6",
                                    "name": "Forms-3"
                                }
                            ]
                        }]
                    },
                    {
                        "key": "1iyaxo",
                        "className": "col-lg-4 col-md-12",
                        "cards": [{
                            "key": "86jp7c",
                            "extraClass": "card card-top card-top-primary",
                            "widgets": [{
                                    "key": "6tub1h",
                                    "name": "Headers-Heading",
                                    "editable": true,
                                    "dataType": "object",
                                    "wrapper": "card-header",
                                    "data": {
                                        "title": "Received SMS (PAID)"
                                    }
                                },
                                {
                                    "key": "ds719",
                                    "name": "TablesAntd-7"
                                }
                            ]
                        }]
                    }
                ]
            }
        ],
        "igsw7m": [{
                "key": "eylsle",
                "columns": [{
                    "key": "anl20d",
                    "className": "col-lg-12",
                    "cards": [{
                        "key": "vreu2c",
                        "extraClass": "card card-top card-top-success",
                        "widgets": [{
                            "key": "0p52jh",
                            "name": "Headers-Heading2",
                            "editable": true,
                            "dataType": "object",
                            "wrapper": "card-header",
                            "data": {
                                "title": "Contacts and Mailing List",
                                "description": "You can manage your contacts and mailing list on this page"
                            }
                        }]
                    }]
                }]
            },
            {
                "key": "vcd2ze",
                "columns": [{
                        "key": "af4n9",
                        "className": "col-lg-4 col-md-12",
                        "cards": [{
                            "key": "otd3f",
                            "extraClass": "card card-top card-top-primary",
                            "widgets": [{
                                    "key": "0jwqms",
                                    "name": "Headers-Heading3",
                                    "editable": true,
                                    "dataType": "object",
                                    "wrapper": "card-header",
                                    "data": {
                                        "title": "Contact List",
                                        "button": "Add New",
                                        "url": "#"
                                    }
                                },
                                {
                                    "key": "5gy07j",
                                    "name": "WidgetsTables-3"
                                }
                            ]
                        }]
                    },
                    {
                        "key": "njbjai",
                        "className": "col-lg-4 col-md-12",
                        "cards": [{
                            "key": "c6e8sm",
                            "extraClass": "card card-top card-top-primary",
                            "widgets": [{
                                    "key": "hiwjiq",
                                    "name": "Headers-Heading",
                                    "editable": true,
                                    "dataType": "object",
                                    "wrapper": "card-header",
                                    "data": {
                                        "title": "Mailing List"
                                    }
                                },
                                {
                                    "key": "yvfr5o",
                                    "name": "TablesAntd-7"
                                }
                            ]
                        }]
                    },
                    {
                        "key": "tr9wmp",
                        "className": "col-lg-4 col-md-12",
                        "cards": [{
                            "key": "v66w0q",
                            "extraClass": "card card-top card-top-primary",
                            "widgets": []
                        }]
                    }
                ]
            }
        ],
        "dfflre": [{
                "key": "zt5ycx",
                "columns": [{
                    "key": "rgntep",
                    "className": "col-lg-12",
                    "cards": [{
                        "key": "6xdcl",
                        "extraClass": "card card-top card-top-success",
                        "widgets": [{
                            "key": "0xicb5",
                            "name": "Headers-Heading",
                            "editable": true,
                            "dataType": "object",
                            "wrapper": "card-header",
                            "data": {
                                "title": "Account Section"
                            }
                        }]
                    }]
                }]
            },
            {
                "key": "cil4xd",
                "columns": [{
                        "key": "ioyhbh",
                        "className": "col-lg-4 col-md-12",
                        "cards": [{
                            "key": "mwka8a",
                            "extraClass": "card card-top card-top-primary",
                            "widgets": [{
                                "key": "apur1",
                                "name": "Typography-3"
                            }]
                        }]
                    },
                    {
                        "key": "vl3hh",
                        "className": "col-lg-8 col-md-12",
                        "cards": [{
                            "key": "6i8o6l",
                            "extraClass": "card card-top card-top-primary",
                            "widgets": [{
                                "key": "d9icua",
                                "name": "Forms-3"
                            }]
                        }]
                    }
                ]
            }
        ],
        "t44kvu": [{
                "key": "4bydc",
                "columns": [{
                    "key": "4vcpjo",
                    "className": "col-lg-12",
                    "cards": [{
                        "key": "ei3wzo",
                        "extraClass": "card card-top card-top-success",
                        "widgets": [{
                            "key": "14v50j",
                            "name": "Headers-Heading",
                            "editable": true,
                            "dataType": "object",
                            "wrapper": "card-header",
                            "data": {
                                "title": "Billing Information"
                            }
                        }]
                    }]
                }]
            },
            {
                "key": "6g25d9",
                "columns": [{
                        "key": "tkcrne",
                        "className": "col-lg-4 col-md-12",
                        "cards": [{
                            "key": "tuq2v",
                            "extraClass": "card card-top card-top-primary",
                            "widgets": [{
                                "key": "tfzuf4",
                                "name": "Typography-3"
                            }]
                        }]
                    },
                    {
                        "key": "mumjhc",
                        "className": "col-lg-8 col-md-12",
                        "cards": [{
                            "key": "l6k4x",
                            "extraClass": "card card-top card-top-primary",
                            "widgets": [{
                                "key": "po98b",
                                "name": "WidgetsGeneral-12v3"
                            }]
                        }]
                    }
                ]
            }
        ],
        "__dashboard": [{
            "key": "r710ti",
            "columns": [{
                    "key": "661k7",
                    "className": "col-lg-4 col-md-12",
                    "cards": [{
                        "key": "ylonm",
                        "extraClass": "card card-top card-top-success",
                        "widgets": [{
                                "key": "oplbup",
                                "name": "Headers-Heading",
                                "editable": true,
                                "dataType": "object",
                                "wrapper": "card-header",
                                "data": {
                                    "title": "Credit"
                                }
                            },
                            {
                                "key": "fet1bg",
                                "name": "WidgetsCharts-11",
                                "wrapper": false
                            }
                        ]
                    }]
                },
                {
                    "key": "ia3eue",
                    "className": "col-lg-4 col-md-12",
                    "cards": [{
                        "key": "53yhu",
                        "extraClass": "card card-top card-top-success",
                        "widgets": [{
                                "key": "xpi95g",
                                "name": "Headers-Heading",
                                "editable": true,
                                "dataType": "object",
                                "wrapper": "card-header",
                                "data": {
                                    "title": "Outgoing"
                                }
                            },
                            {
                                "key": "m7rbgg",
                                "name": "WidgetsCharts-11v1",
                                "wrapper": false
                            }
                        ]
                    }]
                },
                {
                    "key": "5zmon",
                    "className": "col-lg-4 col-md-12",
                    "cards": [{
                        "key": "96f26f",
                        "extraClass": "card card-top card-top-success",
                        "widgets": [{
                                "key": "rg2mbh",
                                "name": "Headers-Heading",
                                "editable": true,
                                "dataType": "object",
                                "wrapper": "card-header",
                                "data": {
                                    "title": "Mbasela"
                                }
                            },
                            {
                                "key": "ht3w1",
                                "name": "WidgetsCharts-11v2",
                                "wrapper": false
                            }
                        ]
                    }]
                }
            ]
        }]
    }
}